hatch_babel/__init__.py
hatch_babel-0.1.2.dist-info/METADATA
hatch_babel-0.1.2.dist-info/WHEEL
hatch_babel-0.1.2.dist-info/entry_points.txt
hatch_babel-0.1.2.dist-info/licenses/LICENSE
hatch_babel-0.1.2.dist-info/RECORD
