Metadata-Version: 2.4
Name: hatch-babel
Version: 0.1.2
Summary: A hatch build-hook for compiling babel .po files to .mo files.
Author-email: Niklas Rosenstein <rosensteinniklas@gmail.com>
License: MIT
License-File: LICENSE
Classifier: Framework :: Hatch
Requires-Python: >=3.10
Requires-Dist: babel>=2.16.0
Requires-Dist: hatchling>=1.27.0
Requires-Dist: typing-extensions>=4.12.2
